{
  "/": {
    "percentage": null,
    "totalStatements": null,
    "coveredStatements": null
  },
  "/server.js": {
    "percentage": null,
    "totalStatements": null,
    "coveredStatements": null,
    "testables": []
  },
  "/config": {
    "percentage": null,
    "totalStatements": null,
    "coveredStatements": null
  },
  "/config/db.js": {
    "percentage": null,
    "totalStatements": null,
    "coveredStatements": null,
    "testables": [
      {
        "name": "connectDB",
        "percentage": null,
        "totalStatements": null,
        "coveredStatements": null
      },
      {
        "name": "connectDB",
        "percentage": null,
        "totalStatements": null,
        "coveredStatements": null
      }
    ]
  },
  "/controllers": {
    "percentage": null,
    "totalStatements": null,
    "coveredStatements": null
  },
  "/controllers/authController.js": {
    "percentage": null,
    "totalStatements": null,
    "coveredStatements": null,
    "testables": [
      {
        "name": "generateToken",
        "percentage": null,
        "totalStatements": null,
        "coveredStatements": null
      },
      {
        "name": "register",
        "percentage": null,
        "totalStatements": null,
        "coveredStatements": null
      },
      {
        "name": "login",
        "percentage": null,
        "totalStatements": null,
        "coveredStatements": null
      },
      {
        "name": "getMe",
        "percentage": null,
        "totalStatements": null,
        "coveredStatements": null
      }
    ]
  },
  "/controllers/eventController.js": {
    "percentage": null,
    "totalStatements": null,
    "coveredStatements": null,
    "testables": [
      {
        "name": "getAllEvents",
        "percentage": null,
        "totalStatements": null,
        "coveredStatements": null
      },
      {
        "name": "getEvent",
        "percentage": null,
        "totalStatements": null,
        "coveredStatements": null
      },
      {
        "name": "createEvent",
        "percentage": null,
        "totalStatements": null,
        "coveredStatements": null
      },
      {
        "name": "updateEvent",
        "percentage": null,
        "totalStatements": null,
        "coveredStatements": null
      },
      {
        "name": "deleteEvent",
        "percentage": null,
        "totalStatements": null,
        "coveredStatements": null
      },
      {
        "name": "enrollVolunteer",
        "percentage": null,
        "totalStatements": null,
        "coveredStatements": null
      },
      {
        "name": "unenrollVolunteer",
        "percentage": null,
        "totalStatements": null,
        "coveredStatements": null
      }
    ]
  },
  "/controllers/statsController.js": {
    "percentage": null,
    "totalStatements": null,
    "coveredStatements": null,
    "testables": [
      {
        "name": "getStats",
        "percentage": null,
        "totalStatements": null,
        "coveredStatements": null
      }
    ]
  },
  "/controllers/volunteerController.js": {
    "percentage": null,
    "totalStatements": null,
    "coveredStatements": null,
    "testables": [
      {
        "name": "getAllVolunteers",
        "percentage": null,
        "totalStatements": null,
        "coveredStatements": null
      },
      {
        "name": "getVolunteer",
        "percentage": null,
        "totalStatements": null,
        "coveredStatements": null
      },
      {
        "name": "createVolunteer",
        "percentage": null,
        "totalStatements": null,
        "coveredStatements": null
      },
      {
        "name": "updateVolunteer",
        "percentage": null,
        "totalStatements": null,
        "coveredStatements": null
      },
      {
        "name": "deleteVolunteer",
        "percentage": null,
        "totalStatements": null,
        "coveredStatements": null
      },
      {
        "name": "updateHours",
        "percentage": null,
        "totalStatements": null,
        "coveredStatements": null
      }
    ]
  },
  "/middleware": {
    "percentage": null,
    "totalStatements": null,
    "coveredStatements": null
  },
  "/middleware/authMiddleware.js": {
    "percentage": null,
    "totalStatements": null,
    "coveredStatements": null,
    "testables": [
      {
        "name": "protect",
        "percentage": null,
        "totalStatements": null,
        "coveredStatements": null
      },
      {
        "name": "adminOnly",
        "percentage": null,
        "totalStatements": null,
        "coveredStatements": null
      }
    ]
  },
  "/models": {
    "percentage": null,
    "totalStatements": null,
    "coveredStatements": null
  },
  "/models/Event.js": {
    "percentage": null,
    "totalStatements": null,
    "coveredStatements": null,
    "testables": []
  },
  "/models/User.js": {
    "percentage": null,
    "totalStatements": null,
    "coveredStatements": null,
    "testables": [
      {
        "name": "matchPassword",
        "percentage": null,
        "totalStatements": null,
        "coveredStatements": null
      }
    ]
  },
  "/models/Volunteer.js": {
    "percentage": null,
    "totalStatements": null,
    "coveredStatements": null,
    "testables": []
  },
  "/routes": {
    "percentage": null,
    "totalStatements": null,
    "coveredStatements": null
  },
  "/routes/authRoutes.js": {
    "percentage": null,
    "totalStatements": null,
    "coveredStatements": null,
    "testables": []
  },
  "/routes/eventRoutes.js": {
    "percentage": null,
    "totalStatements": null,
    "coveredStatements": null,
    "testables": []
  },
  "/routes/statsRoutes.js": {
    "percentage": null,
    "totalStatements": null,
    "coveredStatements": null,
    "testables": []
  },
  "/routes/volunteerRoutes.js": {
    "percentage": null,
    "totalStatements": null,
    "coveredStatements": null,
    "testables": []
  }
}